bar_raiser-0.0.10.dist-info/METADATA
bar_raiser-0.0.10.dist-info/WHEEL
bar_raiser-0.0.10.dist-info/entry_points.txt
bar_raiser-0.0.10.dist-info/licenses/LICENSE
bar_raiser/__init__.py
bar_raiser/autofixes/__init__.py
bar_raiser/autofixes/notify_reviewer_teams.py
bar_raiser/checks/__init__.py
bar_raiser/checks/annotate_diff_cover.py
bar_raiser/checks/annotate_merge_commits.py
bar_raiser/checks/annotate_pyright.py
bar_raiser/checks/annotate_pytest.py
bar_raiser/checks/annotate_ruff.py
bar_raiser/codemods/__init__.py
bar_raiser/codemods/remove_unnecessary_pyright_ignore_comments.py
bar_raiser/tech_debt_framework/__init__.py
bar_raiser/tech_debt_framework/analyzers/__init__.py
bar_raiser/tech_debt_framework/analyzers/pyright.py
bar_raiser/tech_debt_framework/run_analyzers.py
bar_raiser/tech_debt_framework/utils.py
bar_raiser/utils/__init__.py
bar_raiser/utils/check.py
bar_raiser/utils/github.py
bar_raiser/utils/slack.py
bar_raiser-0.0.10.dist-info/RECORD
