Metadata-Version: 2.1
Name: bar-raiser
Version: 0.0.10
Summary: Bar-Raiser is a cutting-edge framework designed to help engineering teams tackle technical debt, streamline development workflows, and elevate code quality.
Author-Email: Jimmy Lai <jimmy.lai@ziphq.com>
License: BSD-3-Clause
Requires-Python: >=3.11
Requires-Dist: pygithub>=2.2.0
Requires-Dist: gitpython>=3.1.41
Requires-Dist: cryptography>=42.0.4
Requires-Dist: slackclient>=2.7.2
Requires-Dist: libcst>=1.1.0
Requires-Dist: fixit==0.1.4
Requires-Dist: aioboto3>=13.0.0
Requires-Dist: boto3>=1.34.106
Requires-Dist: setuptools>=68.0.0
